pylogus/__init__.py
pylogus/pylogus.py
pylogus/version.py
pylogus-0.1.0.dist-info/LICENSE
pylogus-0.1.0.dist-info/METADATA
pylogus-0.1.0.dist-info/WHEEL
pylogus-0.1.0.dist-info/top_level.txt
pylogus-0.1.0.dist-info/RECORD
