Metadata-Version: 2.1
Name: pylogus
Version: 0.1.0
Summary: Simple log format and other stuff
Home-page: https://github.com/Mcublog/pylog
Author: Viacheslav
Author-email: Viacheslav@mcublog.ru
Classifier: Programming Language :: Python :: 3
Classifier: License :: OSI Approved :: MIT License
Classifier: Operating System :: OS Independent
Requires-Python: >=3.7
License-File: LICENSE
Requires-Dist: colorama
